Metadata-Version: 2.1
Name: hyperliquid-felix
Version: 0.21.0
Summary: SDK for Hyperliquid API trading with Python.
Home-page: https://github.com/hyperliquid-dex/hyperliquid-python-sdk
License: MIT
Author: Hyperliquid
Author-email: hello@hyperliquid.xyz
Requires-Python: >=3.9,<4.0
Classifier: Development Status :: 3 - Alpha
Classifier: Intended Audience :: Developers
Classifier: License :: OSI Approved :: MIT License
Classifier: Operating System :: OS Independent
Classifier: Programming Language :: Python :: 3
Classifier: Programming Language :: Python :: 3.9
Classifier: Programming Language :: Python :: 3.10
Classifier: Programming Language :: Python :: 3.11
Classifier: Programming Language :: Python :: 3.12
Classifier: Programming Language :: Python :: 3.13
Classifier: Topic :: Software Development :: Libraries :: Python Modules
Requires-Dist: eth-account (>=0.10.0,<0.14.0)
Requires-Dist: eth-utils (>=2.1.0,<6.0.0)
Requires-Dist: msgpack (>=1.0.5,<2.0.0)
Requires-Dist: requests (>=2.29.0,<3.0.0)
Requires-Dist: websocket-client (>=1.5.1,<2.0.0)
Project-URL: Repository, https://github.com/hyperliquid-dex/hyperliquid-python-sdk
